langchain_airbyte/__init__.py
langchain_airbyte/document_loaders.py
langchain_airbyte/py.typed
langchain_airbyte-0.1.1.dist-info/LICENSE
langchain_airbyte-0.1.1.dist-info/METADATA
langchain_airbyte-0.1.1.dist-info/WHEEL
langchain_airbyte-0.1.1.dist-info/RECORD
