Metadata-Version: 2.1
Name: langchain-airbyte
Version: 0.1.1
Summary: An integration package connecting Airbyte and LangChain
Home-page: https://github.com/langchain-ai/langchain
License: MIT
Requires-Python: >=3.9,<4.0
Classifier: License :: OSI Approved :: MIT License
Classifier: Programming Language :: Python :: 3
Classifier: Programming Language :: Python :: 3.9
Classifier: Programming Language :: Python :: 3.10
Classifier: Programming Language :: Python :: 3.11
Classifier: Programming Language :: Python :: 3.12
Requires-Dist: airbyte (>=0.7.3,<0.8.0)
Requires-Dist: langchain-core (>=0.1.5,<0.3)
Requires-Dist: pydantic (>=1.10.8,<2)
Project-URL: Repository, https://github.com/langchain-ai/langchain
Project-URL: Source Code, https://github.com/langchain-ai/langchain/tree/master/libs/partners/airbyte
